odoo8_addon_product_links-8.0.1.0.1.99.dev26-py2.7-nspkg.pth
odoo8_addon_product_links-8.0.1.0.1.99.dev26.dist-info/DESCRIPTION.rst
odoo8_addon_product_links-8.0.1.0.1.99.dev26.dist-info/METADATA
odoo8_addon_product_links-8.0.1.0.1.99.dev26.dist-info/RECORD
odoo8_addon_product_links-8.0.1.0.1.99.dev26.dist-info/WHEEL
odoo8_addon_product_links-8.0.1.0.1.99.dev26.dist-info/metadata.json
odoo8_addon_product_links-8.0.1.0.1.99.dev26.dist-info/namespace_packages.txt
odoo8_addon_product_links-8.0.1.0.1.99.dev26.dist-info/top_level.txt
odoo_addons/product_links/README.rst
odoo_addons/product_links/__init__.py
odoo_addons/product_links/__openerp__.py
odoo_addons/product_links/product_links.py
odoo_addons/product_links/product_links_view.xml
odoo_addons/product_links/i18n/am.po
odoo_addons/product_links/i18n/ar.po
odoo_addons/product_links/i18n/bg.po
odoo_addons/product_links/i18n/bs.po
odoo_addons/product_links/i18n/ca.po
odoo_addons/product_links/i18n/ca_ES.po
odoo_addons/product_links/i18n/cs.po
odoo_addons/product_links/i18n/da.po
odoo_addons/product_links/i18n/de.po
odoo_addons/product_links/i18n/el_GR.po
odoo_addons/product_links/i18n/en_GB.po
odoo_addons/product_links/i18n/es.po
odoo_addons/product_links/i18n/es_AR.po
odoo_addons/product_links/i18n/es_CL.po
odoo_addons/product_links/i18n/es_CO.po
odoo_addons/product_links/i18n/es_CR.po
odoo_addons/product_links/i18n/es_DO.po
odoo_addons/product_links/i18n/es_EC.po
odoo_addons/product_links/i18n/es_ES.po
odoo_addons/product_links/i18n/es_MX.po
odoo_addons/product_links/i18n/es_PE.po
odoo_addons/product_links/i18n/es_PY.po
odoo_addons/product_links/i18n/es_VE.po
odoo_addons/product_links/i18n/et.po
odoo_addons/product_links/i18n/eu.po
odoo_addons/product_links/i18n/fa.po
odoo_addons/product_links/i18n/fi.po
odoo_addons/product_links/i18n/fr.po
odoo_addons/product_links/i18n/fr_CA.po
odoo_addons/product_links/i18n/fr_CH.po
odoo_addons/product_links/i18n/fr_FR.po
odoo_addons/product_links/i18n/gl.po
odoo_addons/product_links/i18n/gl_ES.po
odoo_addons/product_links/i18n/he.po
odoo_addons/product_links/i18n/hr.po
odoo_addons/product_links/i18n/hr_HR.po
odoo_addons/product_links/i18n/hu.po
odoo_addons/product_links/i18n/id.po
odoo_addons/product_links/i18n/it.po
odoo_addons/product_links/i18n/ja.po
odoo_addons/product_links/i18n/ko.po
odoo_addons/product_links/i18n/lt.po
odoo_addons/product_links/i18n/lt_LT.po
